wifi_connection/__init__.py
wifi_connection/__main__.py
wifi_connection/main.py
wifi_connection/wlanapi.py
wifi_connection/wlanapi_para.py
wifi_connection/wlanapidll.py
wifi_connection-0.1.14.dist-info/entry_points.txt
wifi_connection-0.1.14.dist-info/METADATA
wifi_connection-0.1.14.dist-info/WHEEL
wifi_connection-0.1.14.dist-info/RECORD
