Metadata-Version: 2.1
Name: wifi-connection
Version: 0.1.14
Summary: 
Author: grace tung
Author-email: gracetung29@gmail.com
Requires-Python: >=3.9,<4.0
Classifier: Programming Language :: Python :: 3
Classifier: Programming Language :: Python :: 3.9
Classifier: Programming Language :: Python :: 3.10
Classifier: Programming Language :: Python :: 3.11
Classifier: Programming Language :: Python :: 3.12
Requires-Dist: typer[all] (>=0.9.0,<0.10.0)
Requires-Dist: wmi (>=1.5.1,<2.0.0)
